{"cameraMode":{"drawMode":0,"name":"Shaded","section":"Shading Mode"},"sceneLighting":true,"audioPlay":false,"sceneViewState":{"showFog":true,"showMaterialUpdate":false,"showSkybox":true,"showFlares":true,"showImageEffects":true,"showParticleSystems":true,"showVisualEffectGraphs":true,"m_FxEnabled":true},"in2DMode":false,"pivot":{"x":285.4250183105469,"y":-0.9158605933189392,"z":111.28269958496094},"rotation":{"x":-0.16111163794994355,"y":-0.20069241523742677,"z":0.03348565474152565,"w":-0.9657171368598938},"size":10.0,"orthographic":false}